DSSATTools/__init__.py
DSSATTools/crop.py
DSSATTools/filex.py
DSSATTools/run.py
DSSATTools/soil.py
DSSATTools/weather.py
DSSATTools/base/__init__.py
DSSATTools/base/partypes.py
DSSATTools/base/utils.py
DSSATTools/bin/dscsm048
DSSATTools/bin/dscsm048.exe
DSSATTools/dssat-csm-os/Data/DATA.CDE
DSSATTools/dssat-csm-os/Data/DETAIL.CDE
DSSATTools/dssat-csm-os/Data/DSCSM048.CTR
DSSATTools/dssat-csm-os/Data/DSSATPRO.L48.in
DSSATTools/dssat-csm-os/Data/DSSATPRO.v48
DSSATTools/dssat-csm-os/Data/ECONOMIC.CDE
DSSATTools/dssat-csm-os/Data/GCOEFF.CDE
DSSATTools/dssat-csm-os/Data/GRSTAGE.CDE
DSSATTools/dssat-csm-os/Data/JDATE.CDE
DSSATTools/dssat-csm-os/Data/MODEL.ERR
DSSATTools/dssat-csm-os/Data/OUTPUT.CDE
DSSATTools/dssat-csm-os/Data/PEST.CDE
DSSATTools/dssat-csm-os/Data/SIMULATION.CDE
DSSATTools/dssat-csm-os/Data/SOIL.CDE
DSSATTools/dssat-csm-os/Data/WEATHER.CDE
DSSATTools/dssat-csm-os/Data/Default/Simulate.def
DSSATTools/dssat-csm-os/Data/Default/Simulate_Forecast.def
DSSATTools/dssat-csm-os/Data/Default/Simulate_Seasonal.def
DSSATTools/dssat-csm-os/Data/Default/Simulate_Sequence.def
DSSATTools/dssat-csm-os/Data/Default/Simulate_Spatial.def
DSSATTools/dssat-csm-os/Data/Default/Weather.var
DSSATTools/dssat-csm-os/Data/Genotype/ALFRM048.CUL
DSSATTools/dssat-csm-os/Data/Genotype/ALFRM048.ECO
DSSATTools/dssat-csm-os/Data/Genotype/ALFRM048.SPE
DSSATTools/dssat-csm-os/Data/Genotype/BACER048.CUL
DSSATTools/dssat-csm-os/Data/Genotype/BACER048.ECO
DSSATTools/dssat-csm-os/Data/Genotype/BACER048.SPE
DSSATTools/dssat-csm-os/Data/Genotype/BACRP048.CUL
DSSATTools/dssat-csm-os/Data/Genotype/BACRP048.ECO
DSSATTools/dssat-csm-os/Data/Genotype/BACRP048.SPE
DSSATTools/dssat-csm-os/Data/Genotype/BCGRO048.CUL
DSSATTools/dssat-csm-os/Data/Genotype/BCGRO048.ECO
DSSATTools/dssat-csm-os/Data/Genotype/BCGRO048.SPE
DSSATTools/dssat-csm-os/Data/Genotype/BHGRO048.CUL
DSSATTools/dssat-csm-os/Data/Genotype/BHGRO048.ECO
DSSATTools/dssat-csm-os/Data/Genotype/BHGRO048.SPE
dssattools-3.0.1.dist-info/licenses/LICENSE
dssattools-3.0.1.dist-info/METADATA
dssattools-3.0.1.dist-info/WHEEL
dssattools-3.0.1.dist-info/top_level.txt
dssattools-3.0.1.dist-info/RECORD
