Metadata-Version: 2.4
Name: DSSATTools
Version: 3.0.1
Summary: A DSSAT's Python implementation
Home-page: https://github.com/daquinterop/Py_DSSATTools
Author: Diego Quintero
Author-email: daquinterop@gmail.com
License: MIT
Project-URL: Bug Tracker, https://github.com/daquinterop/Py_DSSATTools/issues
Project-URL: Documentation, https://py-dssattools.readthedocs.io/en/latest/
Classifier: Programming Language :: Python :: 3
Classifier: License :: OSI Approved :: MIT License
Classifier: Operating System :: OS Independent
Requires-Python: >=3.6
License-File: LICENSE
Requires-Dist: attrs
Requires-Dist: certifi
Requires-Dist: chardet
Requires-Dist: charset-normalizer
Requires-Dist: coverage
Requires-Dist: idna
Requires-Dist: iniconfig
Requires-Dist: numpy
Requires-Dist: packaging
Requires-Dist: pandas
Requires-Dist: pluggy
Requires-Dist: py
Requires-Dist: pyparsing
Requires-Dist: pytest
Requires-Dist: pytest-cov
Requires-Dist: python-dateutil
Requires-Dist: pytz
Requires-Dist: requests
Requires-Dist: rosetta-soil
Requires-Dist: six
Requires-Dist: toml
Requires-Dist: tomli
Dynamic: author
Dynamic: author-email
Dynamic: classifier
Dynamic: description
Dynamic: description-content-type
Dynamic: home-page
Dynamic: license
Dynamic: license-file
Dynamic: project-url
Dynamic: requires-dist
Dynamic: requires-python
Dynamic: summary
